{"scores": [{"score": 100, "quantum_score": 100, "time": 1746302047.0399826, "metrics": {"survival_time": 0.024666666666666625, "orbs_collected": 0.0, "enemies_avoided": 0.2}}, {"score": 1, "quantum_score": 1, "time": 1746302039.4173648, "metrics": {"survival_time": 0.022058333333333315, "orbs_collected": 0.0, "enemies_avoided": 0.22}}, {"score": 1, "quantum_score": 1, "time": 1746302039.4211607, "metrics": {"survival_time": 0.022058333333333315, "orbs_collected": 0.0, "enemies_avoided": 0.22}}], "quantum_factor": 0.3086584212985101, "last_updated": 1746302047.0402982}